{
  "users": [
    {
      "id": "1",
      "firstname": "TheFirstname",
      "lastname": "LastSample",
      "middlename": "MiddleSample",
      "birthday": "mm/dd/yyyy",
      "gender": "male",
      "position": "ThePosition",
      "pay": "600",
      "phone": "09123456789",
      "address": "160 Magsaysay St. Miputak Dipolog City, Zamboanga del Norte 7100",
      "username": "sampleuser",
      "password": "samplepass",
      "datecreated": "mm/dd/yyyy"
    },
    {
      "id": "5",
      "firstname": "fiver",
      "lastname": "five",
      "middlename": "fivest",
      "birthday": "birthtest",
      "gender": "Female",
      "position": "Position5",
      "pay": "55555555",
      "phone": "55555555555",
      "address": "5address5address",
      "username": "thefive",
      "password": "12345",
      "datecreated": 1707715800106
    },
    {
      "id": "6",
      "firstname": "Sixer",
      "lastname": "Six",
      "middlename": "Sixx",
      "birthday": "666666",
      "gender": "Male",
      "position": "Position6",
      "pay": "666666",
      "phone": "+666666666",
      "address": "6 Address 6 Address",
      "username": "thesix",
      "password": "123456",
      "datecreated": 1707726949207
    },
    {
      "id": "0297",
      "firstname": "Stradat",
      "lastname": "Stradat",
      "middlename": "Stradat",
      "birthday": "02/14/1997",
      "gender": "Male",
      "position": "IT",
      "pay": "600",
      "phone": "09123455789",
      "address": "Somewhere Over the Rainbow",
      "username": "staradat",
      "password": "stradat",
      "datecreated": "2024/1/14"
    },
    {
      "id": "3543",
      "firstname": "John",
      "lastname": "Doe",
      "middlename": "Samson",
      "birthday": "yyyy/mm/dd",
      "gender": "Male",
      "position": "ThePosition",
      "pay": "600",
      "phone": "091122334455",
      "address": "100 Street St. Barangay City City, Province Province 1100",
      "username": "john",
      "password": "12345",
      "datecreated": "2024/1/15"
    },
    {
      "id": "c2cf",
      "firstname": "Jack",
      "lastname": "Luck",
      "middlename": "Reacher",
      "birthday": "yyyy/mm/dd",
      "gender": "Male",
      "position": "ThePosition",
      "pay": "600",
      "phone": "091122334455",
      "address": "100 Street St. Barangay City City, Province Province 1100",
      "username": "jack",
      "password": "12345",
      "datecreated": "2024/1/19"
    }
  ],
  "files": [
    {
      "id": "1",
      "user": "1",
      "filename": "File1",
      "src": "/somethingpath",
      "note": "For Something1",
      "datecreated": "mm/dd/yyyy"
    },
    {
      "id": "2",
      "user": "1",
      "filename": "File2",
      "src": "/somethingpath",
      "note": "For Something2",
      "datecreated": "mm/dd/yyyy"
    },
    {
      "id": "3",
      "user": "1",
      "filename": "File2",
      "src": "/somethingpath",
      "note": "For Something3",
      "datecreated": "mm/dd/yyyy"
    }
  ],
  "notes": [
    {
      "id": "bc33"
    },
    {
      "id": "2080",
      "user": "1",
      "title": "Test",
      "badge": "Required",
      "body": "this is a test note",
      "datecreated": "2024/1/16"
    },
    {
      "id": "97e8",
      "user": "1",
      "title": "For More notes",
      "badge": "Misc",
      "body": "Note notes",
      "datecreated": "2024/1/16"
    },
    {
      "id": "51d2",
      "user": "3543",
      "title": "A Note for John",
      "badge": "Urgent",
      "body": "John needs to doo this",
      "datecreated": "2024/1/16"
    }
  ]
}